neo_ai_sdk_py.py
neo_ai_sdk_py-0.1.1.dist-info/METADATA
neo_ai_sdk_py-0.1.1.dist-info/WHEEL
neo_ai_sdk_py-0.1.1.dist-info/RECORD
