Metadata-Version: 2.1
Name: neo-ai-sdk-py
Version: 0.1.1
Summary: 
Author: zimo
Author-email: zimo-go@163.com
Requires-Python: >=3.10,<3.12
Classifier: Programming Language :: Python :: 3
Classifier: Programming Language :: Python :: 3.10
Classifier: Programming Language :: Python :: 3.11
Requires-Dist: dashscope (>=1.22.1,<2.0.0)
Requires-Dist: fastapi (>=0.115.8,<0.116.0)
Requires-Dist: jinja2 (>=3.1.5,<4.0.0)
Requires-Dist: langchain (>=0.3.19,<0.4.0)
Requires-Dist: langchain-community (>=0.3.18,<0.4.0)
Requires-Dist: langchain-openai (>=0.3.6,<0.4.0)
Requires-Dist: langfuse (>=2.59.3,<3.0.0)
Requires-Dist: langgraph (>=0.3.0,<0.4.0)
Requires-Dist: partialjson (>=0.1.0,<0.2.0)
Requires-Dist: sse-starlette (>=2.2.1,<3.0.0)
Requires-Dist: uvicorn (>=0.34.0,<0.35.0)
